CHANGES.txt
LICENSE
MANIFEST.in
README.rst
TODO.txt
pyproject.toml
setup.cfg
setup.py
tox.ini
src/pyramid_debugtoolbar_api_performance/__init__.py
src/pyramid_debugtoolbar_api_performance/panels.py
src/pyramid_debugtoolbar_api_performance/utils.py
src/pyramid_debugtoolbar_api_performance/views.py
src/pyramid_debugtoolbar_api_performance.egg-info/PKG-INFO
src/pyramid_debugtoolbar_api_performance.egg-info/SOURCES.txt
src/pyramid_debugtoolbar_api_performance.egg-info/dependency_links.txt
src/pyramid_debugtoolbar_api_performance.egg-info/not-zip-safe
src/pyramid_debugtoolbar_api_performance.egg-info/requires.txt
src/pyramid_debugtoolbar_api_performance.egg-info/top_level.txt
src/pyramid_debugtoolbar_api_performance/templates/performance_csv.dbtmako
tests/test_config.py